json_api_builder/__init__.py
json_api_builder/builder.py
json_api_builder/db_generator.py
json_api_builder-0.3.1.dist-info/METADATA
json_api_builder-0.3.1.dist-info/WHEEL
json_api_builder-0.3.1.dist-info/licenses/LICENSE
json_api_builder-0.3.1.dist-info/RECORD
