Metadata-Version: 2.4
Name: json-api-builder
Version: 0.3.1
Summary: A simple library to build robust REST APIs with automatic CRUD endpoints using FastAPI, SQLModel, and FastCRUD.
Project-URL: Homepage, https://github.com/your-username/json-api-builder
Project-URL: Repository, https://github.com/your-username/json-api-builder.git
Author-email: json-api-builder-project <info@example.com>
License-Expression: MIT
License-File: LICENSE
Keywords: api,builder,crud,fastapi,fastcrud,rest,sqlmodel
Classifier: Development Status :: 4 - Beta
Classifier: Framework :: FastAPI
Classifier: Intended Audience :: Developers
Classifier: License :: OSI Approved :: MIT License
Classifier: Programming Language :: Python :: 3
Classifier: Programming Language :: Python :: 3.10
Classifier: Programming Language :: Python :: 3.11
Classifier: Programming Language :: Python :: 3.12
Classifier: Topic :: Internet :: WWW/HTTP
Classifier: Topic :: Software Development :: Libraries :: Python Modules
Requires-Python: >=3.10
Requires-Dist: aiosqlite>=0.19.0
Requires-Dist: fastapi>=0.104.0
Requires-Dist: fastcrud>=0.11.0
Requires-Dist: sqlalchemy-utils<0.42,>=0.41.2
Requires-Dist: sqlmodel>=0.0.19
Requires-Dist: uvicorn[standard]>=0.24.0
Provides-Extra: dev
Requires-Dist: httpx; extra == 'dev'
Requires-Dist: mypy; extra == 'dev'
Requires-Dist: pytest; extra == 'dev'
Requires-Dist: pytest-asyncio; extra == 'dev'
Requires-Dist: ruff; extra == 'dev'
Requires-Dist: vulture; extra == 'dev'
